nlu/__init__.py
nlu/discovery.py
nlu/info.py
nlu/spellbook.py
nlu/components/__init__.py
nlu/components/assertion.py
nlu/components/chunker.py
nlu/components/classifier.py
nlu/components/deidentification.py
nlu/components/embedding.py
nlu/components/embeddings_chunker.py
nlu/components/labeled_dependency_parser.py
nlu/components/lemmatizer.py
nlu/components/matcher.py
nlu/components/nlu_tokenizer.py
nlu/components/normalizer.py
nlu/components/relation.py
nlu/components/resolution.py
nlu/components/sentence_detector.py
nlu/components/sequence2sequence.py
nlu/components/spell_checker.py
nlu/components/stemmer.py
nlu/components/stopwordscleaner.py
nlu/components/unlabeled_dependency_parser.py
nlu/components/util.py
nlu/components/assertions/__init__.py
nlu/components/assertions/assertion_dl/__init__.py
nlu/components/assertions/assertion_dl/assertion_dl.py
nlu/components/assertions/assertion_dl/component_infos.json
nlu/components/assertions/assertion_log_reg/__init__.py
nlu/components/assertions/assertion_log_reg/assertion_log_reg.py
nlu/components/assertions/assertion_log_reg/component_infos.json
nlu/components/chunkers/__init__.py
nlu/components/chunkers/contextual_parser/__init__.py
nlu/components/chunkers/contextual_parser/component_infos.json
nlu/components/chunkers/contextual_parser/contextual_parser.py
nlu/components/chunkers/default_chunker/__init__.py
nlu/components/chunkers/default_chunker/component_infos.json
nlu/components/chunkers/default_chunker/default_chunker.py
nlu/components/chunkers/ngram/__init__.py
nlu/components/chunkers/ngram/component_infos.json
nlu/components/chunkers/ngram/ngram.py
nlu/components/classifiers/__init__.py
nlu/components/classifiers/classifier_dl/__init__.py
nlu/components/classifiers/classifier_dl/classifier_dl.py
nlu/components/classifiers/classifier_dl/component_infos.json
nlu/components/classifiers/generic_classifier/__init__.py
nlu/components/classifiers/generic_classifier/component_infos.json
peanutbutterdatatime-3.4.0.dist-info/LICENSE
peanutbutterdatatime-3.4.0.dist-info/METADATA
peanutbutterdatatime-3.4.0.dist-info/WHEEL
peanutbutterdatatime-3.4.0.dist-info/top_level.txt
peanutbutterdatatime-3.4.0.dist-info/RECORD
